pdm_venv/__init__.py
pdm_venv/backends.py
pdm_venv/commands/__init__.py
pdm_venv/commands/activate.py
pdm_venv/commands/create.py
pdm_venv/commands/list.py
pdm_venv/commands/purge.py
pdm_venv/commands/remove.py
pdm_venv/config.py
pdm_venv/plugin.py
pdm_venv/utils.py
pdm_venv-0.6.0.dist-info/entry_points.txt
pdm_venv-0.6.0.dist-info/WHEEL
pdm_venv-0.6.0.dist-info/METADATA
pdm_venv-0.6.0.dist-info/license_files/LICENSE
pdm_venv-0.6.0.dist-info/RECORD
