Metadata-Version: 2.1
Name: pdm-venv
Version: 0.6.0
Summary: (Deprecated)A plugin for pdm that enables virtualenv management
License: MIT
Author-email: Frost Ming <mianghong@gmail.com>
Requires-Python: >=3.7
Classifier: Development Status :: 4 - Beta
Classifier: License :: OSI Approved :: MIT License
Classifier: Programming Language :: Python :: 3
Classifier: Programming Language :: Python :: 3.10
Classifier: Programming Language :: Python :: 3.7
Classifier: Programming Language :: Python :: 3.8
Classifier: Programming Language :: Python :: 3.9
Requires-Dist: pdm<2,>=1.13.0
Requires-Dist: platformdirs>=2.4
Requires-Dist: virtualenv>=20.4
Provides-Extra: doc
Requires-Dist: mkdocs>=1.1; extra == "doc"
Requires-Dist: mkdocs-material>=6.2; extra == "doc"
Project-URL: Documentation, https://pdm-project.github.io/pdm-venv
Project-URL: Homepage, https://github.com/pdm-project/pdm-venv
Project-URL: Repository, https://github.com/pdm-project/pdm-venv
